robothub/__init__.py
robothub/application.py
robothub/decorators.py
robothub/events.py
robothub/frame_buffer.py
robothub/live_view.py
robothub/live_view_utils.py
robothub/types.py
robothub/utils.py
robothub/replay/__init__.py
robothub/replay/capture_manager.py
robothub/replay/captures.py
robothub/replay/replay_builder.py
robothub/replay/replay_camera.py
robothub/replay/utils.py
robothub/robothub_core_wrapper/__init__.py
robothub/robothub_core_wrapper/_event_typechecks.py
robothub/robothub_core_wrapper/_exceptions.py
robothub/robothub_core_wrapper/_metadata.py
robothub/robothub_core_wrapper/_stop_event.py
robothub/robothub_core_wrapper/_utils.py
robothub/robothub_core_wrapper/app.py
robothub/robothub_core_wrapper/client.py
robothub/robothub_core_wrapper/communicator.py
robothub/robothub_core_wrapper/device.py
robothub/robothub_core_wrapper/events.py
robothub/robothub_core_wrapper/globals.py
robothub/robothub_core_wrapper/streams.py
robothub-2.6.0.dist-info/LICENSE
robothub-2.6.0.dist-info/METADATA
robothub-2.6.0.dist-info/WHEEL
robothub-2.6.0.dist-info/top_level.txt
robothub-2.6.0.dist-info/RECORD
